Lab3/lab3/ex7/sat_count.v
module sat_count(clk, reset, branch, taken, prediction);
   parameter N=2;
   input clk, reset, branch, taken;
   output prediction;
   
   reg[N:0] counter;
   reg prediction;
   
   initial
   begin
        counter = 0;
   end
   
    always@ (posedge clk,reset,branch, taken)
    begin
        if (counter >= 2**(N-1))
        begin
            prediction = 1;
            $display("debug2\n");
            end
        else
            prediction = 0;
    end
   
   always @(reset, taken)
   begin

        if(reset == 1)
            counter = 0;
        else if(branch == 1)
        begin
            if(taken == 0)
            begin
                if(counter != 0)
                    counter = counter - 1;
            end
            else // taken == 1
            begin
                if(counter != 2**N-1)
                begin
                    counter = counter + 1;
                    $display("debug1 - counter: %d\n", counter);
                end
            end
       end
   end
   
   

endmodule

Lab3/lab3/ex7/sat_count_tb.v
module	sat_count_tb;

reg clk, reset, branch, taken;
wire prediction2bit;
wire prediction3bit;
wire prediction4bit;

integer err_num;
reg tmp;

always #5 clk = ~clk;

sat_count sat_count_2bit(clk, reset, branch, taken, prediction2bit);
sat_count #(3) sat_count_5bit(clk, reset, branch, taken, prediction3bit);
sat_count #(4) sat_count_10bit(clk, reset, branch, taken, prediction4bit);


initial begin
	err_num = 0;

	$dumpfile("waves.vcd");
	$dumpvars;

    reset <= 1;
    #5
    reset <= 0;
    #5
    
    if(prediction2bit != 0 || prediction3bit !=0 || prediction4bit != 0 )
    begin
        err_num = err_num + 1;
        $display( "Error in reset=1");
    end
    
    //1
	taken <= 1;
    #5
    branch <= 1;
    #5

    if(prediction2bit != 0 || prediction3bit != 0 || prediction4bit != 0 )
    begin
        err_num = err_num + 1;
        $display("Error in #1 branch\n");
        $display("prediction2bit: %d (0),prediction3bit: %d(0), prediction4bit %d(0)\n",prediction2bit,prediction3bit,prediction4bit);
    end
    
    branch <= 0;
    #5
    
    //2
	taken <= 1;
    #5
    branch <= 1;
    #5
    
    if(prediction2bit != 1 || prediction3bit != 0 || prediction4bit != 0 )
    begin
        err_num = err_num + 1;
        $display( "Error in #2 branch");
        $display("prediction2bit: %d (1),prediction3bit: %d(0), prediction4bit %d(0)\n",prediction2bit,prediction3bit,prediction4bit);
    end
    
    branch <= 0;
    #5

    
    //3
    taken <= 1;
    #5
	branch <= 1;
    #5
    
    if(prediction2bit != 1 || prediction3bit != 0 || prediction4bit != 0 )
    begin
        err_num = err_num + 1;
        $display( "Error in #3 branch");
        $display("prediction2bit: %d (1),prediction3bit: %d(0), prediction4bit %d(0)\n",prediction2bit,prediction3bit,prediction4bit);
    end
    
    branch <= 0;
    #5

    
    //4
    taken <= 1;
    #5
	branch <= 1;
    #5
    
    if(prediction2bit != 1 || prediction3bit != 1 || prediction4bit != 0 )
    begin
        err_num = err_num + 1;
        $display( "Error in #4 branch");
        $display("prediction2bit: %d (1),prediction3bit: %d(1), prediction4bit %d(0)\n",prediction2bit,prediction3bit,prediction4bit);
    end
    
    branch <= 0;
    #5

    
    //5
    taken <= 1;
    #5
	branch <= 1;
    #5
    
    if(prediction2bit != 1 || prediction3bit !=1 || prediction4bit != 0 )
    begin
        err_num = err_num + 1;
        $display( "Error in #5 branch");
        $display("prediction2bit: %d (1),prediction3bit: %d(1), prediction4bit %d(0)\n",prediction2bit,prediction3bit,prediction4bit);
    end
    
    branch <= 0;
    #5

    
    //6
	taken <= 1;
    #5
	branch <= 1;
    #5
    if(prediction2bit != 1 || prediction3bit != 1 || prediction4bit != 0 )
    begin
        err_num = err_num + 1;
        $display( "Error in #6 branch");
        $display("prediction2bit: %d (1),prediction3bit: %d(1), prediction4bit %d(0)\n",prediction2bit,prediction3bit,prediction4bit);
    end
    
    branch <= 0;
    #5

    
    //7
    taken <= 0;
    #5
	branch <= 1;
    #5
    if(prediction2bit != 1 || prediction3bit != 1 || prediction4bit != 0 )
    begin
        err_num = err_num + 1;
        $display( "Error in #7 branch");
        $display("prediction2bit: %d (1),prediction3bit: %d(1), prediction4bit %d(0)\n",prediction2bit,prediction3bit,prediction4bit);
    end
    branch <= 0;
    #5
    //8
	taken <= 0;
    #5
	branch <= 1;
    #5
    if(prediction2bit != 0 || prediction3bit != 1 || prediction4bit != 0 )
    begin
        err_num = err_num + 1;
        $display( "Error in #8 branch");
        $display("prediction2bit: %d (0),prediction3bit: %d(1), prediction4bit %d(0)\n",prediction2bit,prediction3bit,prediction4bit);
    end
    branch <= 0;
    #5
    
    //9
    taken <= 0;
    #5
	branch <= 1;
    #5
    if(prediction2bit != 0 || prediction3bit != 0 || prediction4bit != 0 )
    begin
        err_num = err_num + 1;
        $display( "Error in #9 branch");
        $display("prediction2bit: %d (0),prediction3bit: %d(0), prediction4bit %d(0)\n",prediction2bit,prediction3bit,prediction4bit);
    end
    
    branch <= 0;
    #5
    
    //10
    taken <= 1;
    #5
	branch <= 1;
    #5
    if(prediction2bit != 0 || prediction3bit != 1 || prediction4bit != 0 )
    begin
        err_num = err_num + 1;
        $display( "Error in #10 branch");
        $display("prediction2bit: %d (0),prediction3bit: %d(1), prediction4bit %d(0)\n",prediction2bit,prediction3bit,prediction4bit);
    end
    
    branch<=0;
    #5
    
    //11
    taken <= 1;
    tmp = prediction2bit;
    #5
    branch <= 1;
    #5
    if(prediction2bit != 1 || prediction3bit != 1 || prediction4bit != 0 )
    begin
        err_num = err_num + 1;
        $display( "Error in #11 branch");
        $display("prediction2bit: %d (1),prediction3bit: %d(1), prediction4bit %d(0)\n",prediction2bit,prediction3bit,prediction4bit);
    end
    
    if (tmp == prediction2bit)
    begin
        err_num = err_num + 1;
        $display( "Error in #11 branch - update timing");
    end
    
    branch<=0;
    #5
    
    //12
    taken <= 0;
    #5
	branch <= 0;
    #5
    if(prediction2bit != 1 || prediction3bit != 1 || prediction4bit != 0 )
    begin
        err_num = err_num + 1;
        $display( "Error in #12 (no) branch");
        $display("prediction2bit: %d (1),prediction3bit: %d(1), prediction4bit %d(0)\n",prediction2bit,prediction3bit,prediction4bit);
    end
    
    branch<=0;
    #5
    
    //13
	taken <= 0;
    #5
	branch <= 0;
    #5
    if(prediction2bit != 1 || prediction3bit != 1 || prediction4bit != 0 )
    begin
        err_num = err_num + 1;
        $display( "Error in #13 (no) branch");
        $display("prediction2bit: %d (01),prediction3bit: %d(1), prediction4bit %d(0)\n",prediction2bit,prediction3bit,prediction4bit);
    end
    
    branch<=0;
    #5
    
    //14
    taken <= 1;
    #5
    if(prediction2bit != 1 || prediction3bit != 1 || prediction4bit != 0 )
    begin
        err_num = err_num + 1;
        $display( "Error in #14 (no) branch");
        $display("prediction2bit: %d (1),prediction3bit: %d(1), prediction4bit %d(0)\n",prediction2bit,prediction3bit,prediction4bit);
    end
    
    branch<=0;
    #5
    
    //15
	reset <= 1;
    #5
    if(prediction2bit != 0 || prediction3bit != 0 || prediction4bit != 0 )
    begin
        err_num = err_num + 1;
        $display( "Error in #15 reset");
        $display("prediction2bit: %d (0),prediction3bit: %d(0), prediction4bit %d(0)\n",prediction2bit,prediction3bit,prediction4bit);
    end
    
    reset <= 0;
    #5
    branch<=0;
    #5
    
    //16
	taken <= 1;
    #5
	branch <= 1;
    #5
    if(prediction2bit != 0 || prediction3bit != 0 || prediction4bit != 0 )
    begin
        err_num = err_num + 1;
        $display( "Error in #16 branch");
        $display("prediction2bit: %d (0),prediction3bit: %d(0), prediction4bit %d(0)\n",prediction2bit,prediction3bit,prediction4bit);
    end
    
    branch<=0;
    #5
    
    //17
	taken <= 1;
    #5
	branch <= 1;
    #5
    if(prediction2bit != 1 || prediction3bit != 0 || prediction4bit != 0 )
    begin
        err_num = err_num + 1;
        $display( "Error in #17 branch");
        $display("prediction2bit: %d (1),prediction3bit: %d(0), prediction4bit %d(0)\n",prediction2bit,prediction3bit,prediction4bit);
    end
    
    branch<=0;
    #5
    
    //18
	taken <= 1;
    #5
	branch <= 1;
    #5
    if(prediction2bit != 1 || prediction3bit != 0 || prediction4bit != 0 )
    begin
        err_num = err_num + 1;
        $display( "Error in #18 branch");
        $display("prediction2bit: %d (1),prediction3bit: %d(0), prediction4bit %d(0)\n",prediction2bit,prediction3bit,prediction4bit);
    end
    
    branch<=0;
    #5
    
    
	if( err_num==0 )
		$display( "\nPASSED ALL TESTS\n" );
	else
		$display( "\nFail, error number = %d\n", err_num );
	
	#10 $finish;
	end


endmodule

Lab3/lab3/ex7/waves.vcd
$date
    Dec 17, 2018  19:00:00
$end
$version
    TOOL:	ncsim(64)	14.10-s021
$end
$timescale
    1 ns
$end

$scope module sat_count_tb $end
$var reg       1 !    clk  $end
$var reg       1 "    reset  $end
$var reg       1 #    branch  $end
$var reg       1 $    taken  $end
$var wire      1 %    prediction2bit  $end
$var wire      1 &    prediction3bit  $end
$var wire      1 '    prediction4bit  $end
$var integer  32 (    err_num  $end
$var reg       1 )    tmp  $end

$scope module sat_count_2bit $end
$var parameter 32 *    N  $end
$var wire      1 +    clk  $end
$var wire      1 ,    reset  $end
$var wire      1 -    branch  $end
$var wire      1 .    taken  $end
$var reg       1 /    prediction  $end
$var reg       2 0    counter [1:0] $end
$upscope $end


$scope module sat_count_5bit $end
$var parameter 32 1    N  $end
$var wire      1 2    clk  $end
$var wire      1 3    reset  $end
$var wire      1 4    branch  $end
$var wire      1 5    taken  $end
$var reg       1 6    prediction  $end
$var reg       3 7    counter [2:0] $end
$upscope $end


$scope module sat_count_10bit $end
$var parameter 32 8    N  $end
$var wire      1 9    clk  $end
$var wire      1 :    reset  $end
$var wire      1 ;    branch  $end
$var wire      1 <    taken  $end
$var reg       1 =    prediction  $end
$var reg       4 >    counter [3:0] $end
$upscope $end

$upscope $end

$enddefinitions $end
$dumpvars
b100 8
b11 1
b10 *
x!
1"
x#
x$
0%
0&
0'
b0 (
x)
x+
1,
x-
x.
0/
b0 0
x2
13
x4
x5
06
b0 7
x9
1:
x;
x<
0=
b0 >
$end
#5
0"
0:
03
0,
#10
1$
1<
15
1.
#15
1#
1;
14
1-
b1 >
b1 7
b1 0
#20
0#
0;
04
0-
#30
1#
1;
14
1-
b10 >
b10 7
b10 0
1/
1%
#35
0#
0;
04
0-
#45
1#
1;
14
1-
b11 >
b11 7
b11 0
#50
0#
0;
04
0-
#60
1#
1;
14
1-
b100 >
b100 7
16
1&
#65
0#
0;
04
0-
#75
1#
1;
14
1-
b101 >
b101 7
#80
0#
0;
04
0-
#90
1#
1;
14
1-
b110 >
b110 7
#95
0#
0;
04
0-
#100
0$
0<
05
0.
#105
1#
1;
14
1-
b101 >
b101 7
b10 0
#110
0#
0;
04
0-
#120
1#
1;
14
1-
b100 >
b100 7
b1 0
0/
0%
#125
0#
0;
04
0-
#135
1#
1;
14
1-
b11 >
b11 7
b0 0
06
0&
#140
0#
0;
04
0-
#145
1$
1<
15
1.
#150
1#
1;
14
1-
b100 >
b100 7
b1 0
16
1&
#155
0#
0;
04
0-
#160
0)
#165
1#
1;
14
1-
b101 >
b101 7
b10 0
1/
1%
#170
0#
0;
04
0-
#175
0$
0<
05
0.
#205
1$
1<
15
1.
#215
1"
1:
13
1,
b0 >
b0 7
b0 0
06
0/
0%
0&
#220
0"
0:
03
0,
#235
1#
1;
14
1-
b1 >
b1 7
b1 0
#240
0#
0;
04
0-
#250
1#
1;
14
1-
b10 >
b10 7
b10 0
1/
1%
#255
0#
0;
04
0-
#265
1#
1;
14
1-
b11 >
b11 7
b11 0
#270
0#
0;
04
0-
