Lab3/lab3/ex6/parity.v
module parity(clk, in, reset, out);

  input clk, in, reset;
  output out;

  reg 	  out;
  reg 	  state;

  localparam zero=0, one=1;
  
  wire neg_in;
  not g0(neg_in, in);

  always @(posedge clk)
  begin
    if (reset)
      state <= zero;
    else
      case (state)
        zero:
          state <= in;
        one:
          state <= neg_in;
      endcase
  end

  always @(state) 
  begin
    case (state)
      zero:
        out <= zero;
      one:
        out <= one;
    endcase
  end

endmodule

Lab3/lab3/ex6/parity_tb.v
module main;
   reg in, clk, reset;
   wire out;

   parity p(clk, in, reset, out);

   always #5 clk = ~clk;

   always @(negedge clk)
     begin
	if (!reset)
          $display("time %d: in %b, out %b", $time, in, out);
	in = ($random / 16) % 2;
     end
   
   initial
     begin
        $dumpfile("waves.vcd");
        $dumpvars;
        clk = 0;
	in = 0;
        reset = 1;
        #10
	reset = 0;
        #300;
	@(negedge clk);
	#1;
	if (out == 1)
	  $display("ACCEPT");
        $finish;
     end // initial begin
endmodule

Lab3/lab3/ex6/waves.vcd
$date
    Dec 15, 2018  20:38:09
$end
$version
    TOOL:	ncsim(64)	14.10-s021
$end
$timescale
    1 ns
$end

$scope module main $end
$var reg       1 !    in  $end
$var reg       1 "    clk  $end
$var reg       1 #    reset  $end
$var wire      1 $    out  $end

$scope module p $end
$var wire      1 %    clk  $end
$var wire      1 &    in  $end
$var wire      1 '    reset  $end
$var reg       1 (    out  $end
$var reg       1 )    state  $end
$var parameter 32 *    zero  $end
$var parameter 32 +    one  $end
$var wire      1 ,    neg_in  $end
$upscope $end

$upscope $end

$enddefinitions $end
$dumpvars
b1 +
b0 *
0!
0"
1#
x$
0%
0&
1'
x(
x)
1,
$end
#5
1"
1%
0)
0(
0$
#10
0#
0"
1!
1&
0%
0'
0,
#15
1"
1%
1)
1(
1$
#20
0"
0%
#25
1"
1%
0)
0(
0$
#30
0"
0%
#35
1"
1%
1)
1(
1$
#40
0"
0!
0&
0%
1,
#45
1"
1%
#50
0"
0%
#55
1"
1%
#60
0"
1!
1&
0%
0,
#65
1"
1%
0)
0(
0$
#70
0"
0!
0&
0%
1,
#75
1"
1%
#80
0"
0%
#85
1"
1%
#90
0"
0%
#95
1"
1%
#100
0"
1!
1&
0%
0,
#105
1"
1%
1)
1(
1$
#110
0"
0%
#115
1"
1%
0)
0(
0$
#120
0"
0!
0&
0%
1,
#125
1"
1%
#130
0"
0%
#135
1"
1%
#140
0"
1!
1&
0%
0,
#145
1"
1%
1)
1(
1$
#150
0"
0%
#155
1"
1%
0)
0(
0$
#160
0"
0%
#165
1"
1%
1)
1(
1$
#170
0"
0%
#175
1"
1%
0)
0(
0$
#180
0"
0!
0&
0%
1,
#185
1"
1%
#190
0"
0%
#195
1"
1%
#200
0"
0%
#205
1"
1%
#210
0"
0%
#215
1"
1%
#220
0"
1!
1&
0%
0,
#225
1"
1%
1)
1(
1$
#230
0"
0%
#235
1"
1%
0)
0(
0$
#240
0"
0%
#245
1"
1%
1)
1(
1$
#250
0"
0%
#255
1"
1%
0)
0(
0$
#260
0"
0%
#265
1"
1%
1)
1(
1$
#270
0"
0!
0&
0%
1,
#275
1"
1%
#280
0"
1!
1&
0%
0,
#285
1"
1%
0)
0(
0$
#290
0"
0%
#295
1"
1%
1)
1(
1$
#300
0"
0%
#305
1"
1%
0)
0(
0$
#310
0"
0!
0&
0%
1,
