lab4/sram.v
/*****************************************
 * SRAM module: synchronus SRAM, 65536x32
 * 
 * inputs:
 * 
 * clk: system clock
 * addr[15:0]: 16 bit address
 * di[31:0]: 32 bit input data
 * en: enable signal
 * we: write enable (1 write, 0 read)
 ****************************************/
module SRAM(clk, addr, di, en, we, do);

   input clk;
   input [15:0] addr;
   input [31:0] di;
   input 	en;
   input 	we;

   output [31:0] do;
   
   reg [31:0] 	 do;
   reg [31:0] 	 mem[0:65535];
   
   always @(posedge clk)
     begin
	if (en) begin
	   if (we) begin
	      mem[addr] <= di;
	      $display("time %0d: write %08x -> mem[%04x]", $time, di, addr);
	   end
	   else begin
	      do <= mem[addr];
	      $display("time %0d: read mem[%04x] -> %08x", $time, addr, mem[addr]);
	   end
	end
     end
endmodule // sram

Lab4/dma/defines.vh
// control states
`define CTL_STATE_IDLE 0
`define CTL_STATE_FETCH0 1
`define CTL_STATE_FETCH1 2
`define CTL_STATE_DEC0 3
`define CTL_STATE_DEC1 4
`define CTL_STATE_EXEC0 5
`define CTL_STATE_EXEC1 6

// dma states
`define DMA_STATE_IDLE 0
`define DMA_STATE_READ 1
`define DMA_STATE_EXTRACT 2
`define DMA_STATE_WRITE 3

// opcodes
`define ADD 0
`define SUB 1
`define LSF 2
`define RSF 3
`define AND 4
`define OR 5
`define XOR 6
`define LHI 7
`define LD 8
`define ST 9
`define JLT 16
`define JLE 17
`define JEQ 18
`define JNE 19
`define JIN 20
`define HLT 24
`define DMA 30
`define POL 31

Lab4/ctl.v
`include "defines.vh"

/***********************************
 * CTL module
 **********************************/
module CTL(
	   clk,
	   reset,
	   start,
	   sram_ADDR,
	   sram_DI,
	   sram_EN,
	   sram_WE,
	   sram_DO,
	   opcode,
	   alu0,
	   alu1,
	   aluout_wire
	   );

   // inputs
   input clk;
   input reset;
   input start;
   input [31:0] sram_DO;
   input signed [31:0] aluout_wire;

   // outputs
   output [15:0] sram_ADDR;
   output [31:0] sram_DI;
   output 	 sram_EN;
   output 	 sram_WE;
   output signed [31:0] alu0;
   output signed [31:0] alu1;
   output [4:0]  opcode;

   // registers
   reg [31:0] 	 r2;
   reg [31:0] 	 r3;
   reg [31:0] 	 r4;
   reg [31:0] 	 r5;
   reg [31:0] 	 r6;
   reg [31:0] 	 r7;
   reg [15:0] 	 pc;
   reg [31:0] 	 inst;
   reg [4:0] 	 opcode;
   reg [2:0] 	 dst;
   reg [2:0] 	 src0;
   reg [2:0] 	 src1;
   reg [31:0] 	 alu0;
   reg [31:0] 	 alu1;
   reg [31:0] 	 aluout;
   reg [31:0] 	 immediate;
   reg [31:0] 	 cycle_counter;
   reg [2:0] 	 ctl_state;

   integer 	 verilog_trace_fp, rc;
   
   wire [15:0] pc_next = pc + 1;
   
   initial
     begin
	verilog_trace_fp = $fopen("verilog_trace.txt", "w");
     end

	 
	assign sram_DI = alu0;
	assign sram_ADDR = (ctl_state == `CTL_STATE_FETCH0) ? pc : alu1;
	assign sram_EN = 1;
	assign sram_WE = (ctl_state == `CTL_STATE_EXEC1 && opcode == `ST) ? 1 : 0;

   
   // synchronous instructions
   always@(posedge clk)
     begin
	if (reset) begin
	   // registers reset
	   r2 <= 0;
	   r3 <= 0;
	   r4 <= 0;
	   r5 <= 0;
	   r6 <= 0;
	   r7 <= 0;
	   pc <= 0;
	   inst <= 0;
	   opcode <= 0;
	   dst <= 0;
	   src0 <= 0;
	   src1 <= 0;
	   alu0 <= 0;
	   alu1 <= 0;
	   aluout <= 0;
	   immediate <= 0;
	   cycle_counter <= 0;
	   ctl_state <= 0;
	   
	end else begin
	   // generate cycle trace
	   $fdisplay(verilog_trace_fp, "cycle %0d", cycle_counter);
	   $fdisplay(verilog_trace_fp, "r2 %08x", r2);
	   $fdisplay(verilog_trace_fp, "r3 %08x", r3);
	   $fdisplay(verilog_trace_fp, "r4 %08x", r4);
	   $fdisplay(verilog_trace_fp, "r5 %08x", r5);
	   $fdisplay(verilog_trace_fp, "r6 %08x", r6);
	   $fdisplay(verilog_trace_fp, "r7 %08x", r7);
	   $fdisplay(verilog_trace_fp, "pc %08x", pc);
	   $fdisplay(verilog_trace_fp, "inst %08x", inst);
	   $fdisplay(verilog_trace_fp, "opcode %08x", opcode);
	   $fdisplay(verilog_trace_fp, "dst %08x", dst);
	   $fdisplay(verilog_trace_fp, "src0 %08x", src0);
	   $fdisplay(verilog_trace_fp, "src1 %08x", src1);
	   $fdisplay(verilog_trace_fp, "immediate %08x", immediate);
	   $fdisplay(verilog_trace_fp, "alu0 %08x", alu0);
	   $fdisplay(verilog_trace_fp, "alu1 %08x", alu1);
	   $fdisplay(verilog_trace_fp, "aluout %08x", aluout);
	   $fdisplay(verilog_trace_fp, "cycle_counter %08x", cycle_counter);
	   $fdisplay(verilog_trace_fp, "ctl_state %08x\n", ctl_state);

	   cycle_counter <= cycle_counter + 1;
	   case (ctl_state)
	      `CTL_STATE_IDLE: begin
                pc <= 0;
                if (start)
                  ctl_state <= `CTL_STATE_FETCH0;
          end
		  `CTL_STATE_FETCH0: begin
			//sp_trace_exec(spro);
			ctl_state <= `CTL_STATE_FETCH1;
		  end
		  `CTL_STATE_FETCH1: begin
			inst <= sram_DO;
			ctl_state <= `CTL_STATE_DEC0;
		  end
		  `CTL_STATE_DEC0: begin
			opcode <= inst[29:25];
			dst <= inst[24:22];
			src0 <= inst[21:19];
			src1 <= inst[18:16];
			immediate <= {inst[15:0], 16'b0} >>> 16;
			ctl_state <= `CTL_STATE_DEC1;
		  end
		  `CTL_STATE_DEC1: begin
			//sp_trace_inst(spro);
			if (opcode == `LHI) begin
			  alu0 <= readReg (dst);
			  alu1 <= immediate;
			end else begin
			  alu0 <= readReg (src0);
			  alu1 <= readReg (src1);
			end
			ctl_state <= `CTL_STATE_EXEC0;
		  end
		  `CTL_STATE_EXEC0: begin
			aluout <= aluout_wire;
			ctl_state <= `CTL_STATE_EXEC1;
		  end
		  `CTL_STATE_EXEC1: begin
			if (opcode >= `ADD && opcode <= `LHI) begin
				writeReg (dst, aluout);
				pc <= pc_next;
			end else if (opcode == `LD) begin
				writeReg (dst, sram_DO);
				pc <= pc_next;
			end else if (opcode == `ST) begin
				pc <= pc_next;
			end else if (opcode >= `JLT && opcode <= `JNE) begin
				if (aluout) begin
					writeReg (7, pc);
					pc <= immediate;
				end else begin
					pc <= pc_next;
				end
			end else if (opcode == `JIN) begin
				writeReg (7, pc);
				pc <= alu0;
			end
			ctl_state <= `CTL_STATE_FETCH0;
		  end

	   endcase
	   
	   if (opcode == `HLT) begin
	      $fclose(verilog_trace_fp);
	      $writememh("verilog_sram_out.txt", top.SP.SRAM.mem);
	      $finish;
	   end
	end // !reset
     end // @posedge(clk)
	
	function [31:0] readReg;
	    input [2:0] d;
		begin
			case (d)
				0: readReg = 0;
				1: readReg = immediate;
				2: readReg = r2;
				3: readReg = r3;
				4: readReg = r4;
				5: readReg = r5;
				6: readReg = r6;
				7: readReg = r7;
			endcase
		end
	endfunction
	
	task writeReg;
		input [2:0] d;
        input [31:0] v;
		begin
			case (d)
				2: r2 <= v;
				3: r3 <= v;
				4: r4 <= v;
				5: r5 <= v;
				6: r6 <= v;
				7: r7 <= v;
			endcase
		end
	endtask
	
endmodule // CTL

Lab4/alu.v
`include "defines.vh"

/***********************************
 * ALU module
 **********************************/
module ALU(opcode, alu0, alu1, aluout);
   
   input [4:0] opcode;
   input signed [31:0] alu0, alu1;
   output signed [31:0] aluout;
   reg [31:0] 	 aluout;
	
   always@(alu0 or alu1 or opcode)
     begin
	case (opcode)
		`ADD:	aluout <= alu0 + alu1;
		`SUB:	aluout <= alu0 - alu1;
		`LSF:	aluout <= alu0 << alu1;
		`RSF:	aluout <= alu0 >>> alu1;
		`AND:	aluout <= alu0 & alu1;
		`OR:	aluout <= alu0 | alu1;
		`XOR:	aluout <= alu0 ^ alu1;
		`LHI:	aluout <= (alu1 << 16) | alu0[15:0];
		`JLT:	aluout <= (alu0 < alu1);
		`JLE:	aluout <= (alu0 <= alu1);
		`JEQ:	aluout <= (alu0 == alu1);
		`JNE:	aluout <= (alu0 != alu1);

	endcase
     end
endmodule // alu

Lab4/dma/sp.v

/***********************************
 * SP module
 **********************************/
module SP(clk, reset, start);
   input clk;
   input reset;
   input start;

   wire [15:0] sram_ADDR;
   wire [31:0] sram_DI;
   wire        sram_EN;
   wire        sram_WE;
   wire [31:0] sram_DO;
   wire [4:0]  opcode;
   wire [31:0] alu0;
   wire [31:0] alu1;
   wire [31:0] aluout_wire;

   // instantiate ALU, CTL and SRAM modules
   ALU ALU(opcode, alu0, alu1, aluout_wire);
   CTL CTL(
	   clk,
	   reset,
	   start,
	   sram_ADDR,
	   sram_DI,
	   sram_EN,
	   sram_WE,
	   sram_DO,
	   opcode,
	   alu0,
	   alu1,
	   aluout_wire);
   SRAM SRAM(clk, sram_ADDR, sram_DI, sram_EN, sram_WE, sram_DO);
endmodule

Lab4/top.v
`include "sp.v"

/***********************************
 * TOP module
 **********************************/

module top;

   reg clk, reset, start;

   SP SP(clk, reset, start);

   always #5 clk = ~clk;
   
   initial
     begin
	$readmemh("example.bin", top.SP.SRAM.mem);
	clk = 1;     
	reset = 1;
	start = 0;
	$dumpfile("waves.vcd");
	$dumpvars;
	#100;
	reset = 0;
	start = 1;
     end
endmodule // top

Lab4/mult_logs/mult_waves.vcd
$date
    Dec 22, 2018  20:40:55
$end
$version
    TOOL:	ncsim(64)	14.10-s021
$end
$timescale
    1 ns
$end

$scope module top $end
$var reg       1 !    clk  $end
$var reg       1 "    reset  $end
$var reg       1 #    start  $end

$scope module SP $end
$var wire      1 $    clk  $end
$var wire      1 %    reset  $end
$var wire      1 &    start  $end
$var wire     16 '    sram_ADDR [15:0] $end
$var wire     32 (    sram_DI [31:0] $end
$var wire      1 )    sram_EN  $end
$var wire      1 *    sram_WE  $end
$var wire     32 +    sram_DO [31:0] $end
$var wire      5 ,    opcode [4:0] $end
$var wire     32 -    alu0 [31:0] $end
$var wire     32 .    alu1 [31:0] $end
$var wire     32 /    aluout_wire [31:0] $end

$scope module ALU $end
$var wire      5 ,    opcode [4:0] $end
$var wire     32 -    alu0 [31:0] $end
$var wire     32 .    alu1 [31:0] $end
$var reg      32 0    aluout [31:0] $end
$upscope $end


$scope module CTL $end
$var wire      1 $    clk  $end
$var wire      1 %    reset  $end
$var wire      1 &    start  $end
$var wire     32 +    sram_DO [31:0] $end
$var wire     32 /    aluout_wire [31:0] $end
$var wire     16 '    sram_ADDR [15:0] $end
$var wire     32 (    sram_DI [31:0] $end
$var wire      1 )    sram_EN  $end
$var wire      1 *    sram_WE  $end
$var reg      32 1    alu0 [31:0] $end
$var reg      32 2    alu1 [31:0] $end
$var reg       5 3    opcode [4:0] $end
$var reg      32 4    r2 [31:0] $end
$var reg      32 5    r3 [31:0] $end
$var reg      32 6    r4 [31:0] $end
$var reg      32 7    r5 [31:0] $end
$var reg      32 8    r6 [31:0] $end
$var reg      32 9    r7 [31:0] $end
$var reg      16 :    pc [15:0] $end
$var reg      32 ;    inst [31:0] $end
$var reg       3 <    dst [2:0] $end
$var reg       3 =    src0 [2:0] $end
$var reg       3 >    src1 [2:0] $end
$var reg      32 ?    aluout [31:0] $end
$var reg      32 @    immediate [31:0] $end
$var reg      32 A    cycle_counter [31:0] $end
$var reg       3 B    ctl_state [2:0] $end
$var integer  32 C    verilog_trace_fp  $end
$var integer  32 D    rc  $end
$var wire     16 E    pc_next [15:0] $end

$scope function readReg $end
$var reg      32 F    readReg [31:0] $end
$var reg       3 G    d [2:0] $end
$upscope $end


$scope task writeReg $end
$var reg       3 H    d [2:0] $end
$var reg      32 I    v [31:0] $end
$upscope $end

$upscope $end


$scope module SRAM $end
$var wire      1 $    clk  $end
$var wire     16 '    addr [15:0] $end
$var wire     32 (    di [31:0] $end
$var wire      1 )    en  $end
$var wire      1 *    we  $end
$var reg      32 J    do [31:0] $end
$upscope $end

$upscope $end

$upscope $end

$enddefinitions $end
$dumpvars
1!
1"
0#
1$
1%
0&
b0 '
b0 (
1)
0*
bx +
b0 ,
b0 -
b0 .
b0 /
b0 0
b0 1
b0 2
b0 3
b0 4
b0 5
b0 6
b0 7
b0 8
b0 9
b0 :
b0 ;
b0 <
b0 =
b0 >
b0 ?
b0 @
b0 A
b0 B
b10000000000000000000000000000011 C
bx D
b1 E
bx F
bx G
bx H
bx I
bx J
$end
#5
0!
0$
#10
1!
1$
b10000100000010000001111101000 J
b10000100000010000001111101000 +
#15
0!
0$
#20
1!
1$
#25
0!
0$
#30
1!
1$
#35
0!
0$
#40
1!
1$
#45
0!
0$
#50
1!
1$
#55
0!
0$
#60
1!
1$
#65
0!
0$
#70
1!
1$
#75
0!
0$
#80
1!
1$
#85
0!
0$
#90
1!
1$
#95
0!
0$
#100
0"
1#
1!
1$
1&
0%
b1 A
b1 B
#105
0!
0$
#110
1!
1$
b10 A
b10 B
#115
0!
0$
#120
1!
1$
b11 A
b10000100000010000001111101000 ;
b11 B
#125
0!
0$
#130
1!
1$
b100 A
b1000 3
b10 <
b1 >
b1111101000 @
b100 B
b1000 ,
#135
0!
0$
#140
1!
1$
b0 G
b0 F
b1 G
b1111101000 F
b101 A
b1111101000 2
b101 B
b1111101000 '
b1111101000 .
#145
0!
0$
#150
1!
1$
b11111111111111111111111111111110 J
b110 A
b110 B
b11111111111111111111111111111110 +
#155
0!
0$
#160
1!
1$
b10 H
b11111111111111111111111111111110 I
b111 A
b11111111111111111111111111111110 4
b1 :
b1 B
b1 '
b10 E
#165
0!
0$
#170
1!
1$
b10000110000010000001111101001 J
b1000 A
b10 B
b1111101000 '
b10000110000010000001111101001 +
#175
0!
0$
#180
1!
1$
b11111111111111111111111111111110 J
b1001 A
b10000110000010000001111101001 ;
b11 B
b11111111111111111111111111111110 +
#185
0!
0$
#190
1!
1$
b1010 A
b11 <
b1111101001 @
b100 B
#195
0!
0$
#200
1!
1$
b0 G
b0 F
b1 G
b1111101001 F
b1011 A
b1111101001 2
b101 B
b1111101001 '
b1111101001 .
#205
0!
0$
#210
1!
1$
b1010 J
b1100 A
b110 B
b1010 +
#215
0!
0$
#220
1!
1$
b11 H
b1010 I
b1101 A
b1010 5
b10 :
b1 B
b10 '
b11 E
#225
0!
0$
#230
1!
1$
b1100000010000000000000001 J
b1110 A
b10 B
b1111101001 '
b1100000010000000000000001 +
#235
0!
0$
#240
1!
1$
b1010 J
b1111 A
b1100000010000000000000001 ;
b11 B
b1010 +
#245
0!
0$
#250
1!
1$
b10000 A
b0 3
b110 <
b1 @
b100 B
b0 ,
b1111101001 0
b1111101001 /
#255
0!
0$
#260
1!
1$
b0 G
b0 F
b1 G
b1 F
b10001 A
b1 2
b101 B
b1 '
b1 .
b1 0
b1 /
#265
0!
0$
#270
1!
1$
b10000110000010000001111101001 J
b10010 A
b1 ?
b110 B
b10000110000010000001111101001 +
#275
0!
0$
#280
1!
1$
b110 H
b1 I
b10011 A
b1 8
b11 :
b1 B
b11 '
b100 E
#285
0!
0$
#290
1!
1$
b100100000100000000000000011000 J
b10100 A
b10 B
b1 '
b100100000100000000000000011000 +
#295
0!
0$
#300
1!
1$
b10000110000010000001111101001 J
b10101 A
b100100000100000000000000011000 ;
b11 B
b10000110000010000001111101001 +
#305
0!
0$
#310
1!
1$
b10110 A
b10010 3
b0 <
b10 =
b0 >
b11000 @
b100 B
b10010 ,
b0 0
b0 /
#315
0!
0$
#320
1!
1$
b10 G
b11111111111111111111111111111110 F
b0 G
b0 F
b10111 A
b11111111111111111111111111111110 1
b0 2
b101 B
b0 '
b0 .
b11111111111111111111111111111110 (
b11111111111111111111111111111110 -
#325
0!
0$
#330
1!
1$
b10000100000010000001111101000 J
b11000 A
b0 ?
b110 B
b10000100000010000001111101000 +
#335
0!
0$
#340
1!
1$
b11001 A
b100 :
b1 B
b100 '
b101 E
#345
0!
0$
#350
1!
1$
b100100000110000000000000011000 J
b11010 A
b10 B
b0 '
b100100000110000000000000011000 +
#355
0!
0$
#360
1!
1$
b10000100000010000001111101000 J
b11011 A
b100100000110000000000000011000 ;
b11 B
b10000100000010000001111101000 +
#365
0!
0$
#370
1!
1$
b11100 A
b11 =
b100 B
#375
0!
0$
#380
1!
1$
b11 G
b1010 F
b0 G
b0 F
b11101 A
b1010 1
b101 B
b1010 (
b1010 -
#385
0!
0$
#390
1!
1$
b11110 A
b110 B
#395
0!
0$
#400
1!
1$
b11111 A
b101 :
b1 B
b101 '
b110 E
#405
0!
0$
#410
1!
1$
b1101010100110000000000000000 J
b100000 A
b10 B
b0 '
b1101010100110000000000000000 +
#415
0!
0$
#420
1!
1$
b10000100000010000001111101000 J
b100001 A
b1101010100110000000000000000 ;
b11 B
b10000100000010000001111101000 +
#425
0!
0$
#430
1!
1$
b100010 A
b110 3
b101 <
b10 =
b11 >
b0 @
b100 B
b110 ,
b1010 0
b1010 /
#435
0!
0$
#440
1!
1$
b10 G
b11111111111111111111111111111110 F
b11 G
b1010 F
b100011 A
b11111111111111111111111111111110 1
b1010 2
b101 B
b1010 '
b1010 .
b11111111111111111111111111111110 (
b11111111111111111111111111111110 -
b11111111111111111111111111110100 0
b11111111111111111111111111110100 /
#445
0!
0$
#450
1!
1$
b100000000110100000000000010100 J
b100100 A
b11111111111111111111111111110100 ?
b110 B
b100000000110100000000000010100 +
#455
0!
0$
#460
1!
1$
b101 H
b11111111111111111111111111110100 I
b100101 A
b11111111111111111111111111110100 7
b110 :
b1 B
b110 '
b111 E
#465
0!
0$
#470
1!
1$
b100000000000110000000000001000 J
b100110 A
b10 B
b1010 '
b100000000000110000000000001000 +
#475
0!
0$
#480
1!
1$
b100000000110100000000000010100 J
b100111 A
b100000000000110000000000001000 ;
b11 B
b100000000110100000000000010100 +
#485
0!
0$
#490
1!
1$
b101000 A
b10000 3
b0 <
b0 =
b1000 @
b100 B
b10000 ,
b1 0
b1 /
#495
0!
0$
#500
1!
1$
b0 G
b0 F
b11 G
b1010 F
b101001 A
b0 1
b101 B
b0 (
b0 -
#505
0!
0$
#510
1!
1$
b101010 A
b1 ?
b110 B
#515
0!
0$
#520
1!
1$
b111 H
b110 I
b101011 A
b110 9
b1000 :
b1 B
b1000 '
b1001 E
#525
0!
0$
#530
1!
1$
b100000000000100000000000001010 J
b101100 A
b10 B
b1010 '
b100000000000100000000000001010 +
#535
0!
0$
#540
1!
1$
b100000000110100000000000010100 J
b101101 A
b100000000000100000000000001010 ;
b11 B
b100000000110100000000000010100 +
#545
0!
0$
#550
1!
1$
b101110 A
b10 >
b1010 @
b100 B
#555
0!
0$
#560
1!
1$
b0 G
b0 F
b10 G
b11111111111111111111111111111110 F
b101111 A
b11111111111111111111111111111110 2
b101 B
b1111111111111110 '
b11111111111111111111111111111110 .
b0 0
b0 /
#565
0!
0$
#570
1!
1$
bx J
b110000 A
b0 ?
b110 B
bx +
#575
0!
0$
#580
1!
1$
b110001 A
b1001 :
b1 B
b1001 '
b1010 E
#585
0!
0$
#590
1!
1$
b10100000100000000000000000 J
b110010 A
b10 B
b1111111111111110 '
b10100000100000000000000000 +
#595
0!
0$
#600
1!
1$
bx J
b110011 A
b10100000100000000000000000 ;
b11 B
bx +
#605
0!
0$
#610
1!
1$
b110100 A
b1 3
b10 <
b0 @
b100 B
b1 ,
b10 0
b10 /
#615
0!
0$
#620
1!
1$
b0 G
b0 F
b10 G
b11111111111111111111111111111110 F
b110101 A
b101 B
#625
0!
0$
#630
1!
1$
b110110 A
b10 ?
b110 B
#635
0!
0$
#640
1!
1$
b10 H
b10 I
b110111 A
b10 4
b1010 :
b1 B
b1010 '
b1011 E
#645
0!
0$
#650
1!
1$
b100000000110100000000000010100 J
b111000 A
b10 B
b1111111111111110 '
b100000000110100000000000010100 +
#655
0!
0$
#660
1!
1$
bx J
b111001 A
b100000000110100000000000010100 ;
b11 B
bx +
#665
0!
0$
#670
1!
1$
b111010 A
b10000 3
b0 <
b11 =
b10100 @
b100 B
b10000 ,
b0 0
b0 /
#675
0!
0$
#680
1!
1$
b11 G
b1010 F
b10 G
b10 F
b111011 A
b1010 1
b10 2
b101 B
b10 '
b10 .
b1010 (
b1010 -
#685
0!
0$
#690
1!
1$
b1100000010000000000000001 J
b111100 A
b0 ?
b110 B
b1100000010000000000000001 +
#695
0!
0$
#700
1!
1$
b111101 A
b1011 :
b1 B
b1011 '
b1100 E
#705
0!
0$
#710
1!
1$
b100100000101100000000000011010 J
b111110 A
b10 B
b10 '
b100100000101100000000000011010 +
#715
0!
0$
#720
1!
1$
b1100000010000000000000001 J
b111111 A
b100100000101100000000000011010 ;
b11 B
b1100000010000000000000001 +
#725
0!
0$
#730
1!
1$
b1000000 A
b10010 3
b10 =
b110 >
b11010 @
b100 B
b10010 ,
#735
0!
0$
#740
1!
1$
b110 G
b1 F
b1000001 A
b10 1
b1 2
b101 B
b1 '
b1 .
b10 (
b10 -
#745
0!
0$
#750
1!
1$
b10000110000010000001111101001 J
b1000010 A
b110 B
b10000110000010000001111101001 +
#755
0!
0$
#760
1!
1$
b1000011 A
b1100 :
b1 B
b1100 '
b1101 E
#765
0!
0$
#770
1!
1$
b1001000100010000000000000001 J
b1000100 A
b10 B
b1 '
b1001000100010000000000000001 +
#775
0!
0$
#780
1!
1$
b10000110000010000001111101001 J
b1000101 A
b1001000100010000000000000001 ;
b11 B
b10000110000010000001111101001 +
#785
0!
0$
#790
1!
1$
b1000110 A
b100 3
b100 <
b1 >
b1 @
b100 B
b100 ,
#795
0!
0$
#800
1!
1$
b10 G
b10 F
b1 G
b1 F
b1000111 A
b101 B
#805
0!
0$
#810
1!
1$
b1001000 A
b110 B
#815
0!
0$
#820
1!
1$
b100 H
b0 I
b1001001 A
b1101 :
b1 B
b1101 '
b1110 E
#825
0!
0$
#830
1!
1$
b100100001000000000000000010001 J
b1001010 A
b10 B
b1 '
b100100001000000000000000010001 +
#835
0!
0$
#840
1!
1$
b10000110000010000001111101001 J
b1001011 A
b100100001000000000000000010001 ;
b11 B
b10000110000010000001111101001 +
#845
0!
0$
#850
1!
1$
b1001100 A
b10010 3
b0 <
b100 =
b0 >
b10001 @
b100 B
b10010 ,
#855
0!
0$
#860
1!
1$
b100 G
b0 F
b0 G
b1001101 A
b0 1
b0 2
b101 B
b0 '
b0 .
b0 (
b0 -
b1 0
b1 /
#865
0!
0$
#870
1!
1$
b10000100000010000001111101000 J
b1001110 A
b1 ?
b110 B
b10000100000010000001111101000 +
#875
0!
0$
#880
1!
1$
b111 H
b1101 I
b1001111 A
b1101 9
b10001 :
b1 B
b10001 '
b10010 E
#885
0!
0$
#890
1!
1$
b110100100010000000000000001 J
b1010000 A
b10 B
b0 '
b110100100010000000000000001 +
#895
0!
0$
#900
1!
1$
b10000100000010000001111101000 J
b1010001 A
b110100100010000000000000001 ;
b11 B
b10000100000010000001111101000 +
#905
0!
0$
#910
1!
1$
b1010010 A
b11 3
b10 <
b10 =
b1 >
b1 @
b100 B
b11 ,
b0 0
b0 /
#915
0!
0$
#920
1!
1$
b10 G
b10 F
b1 G
b1 F
b1010011 A
b10 1
b1 2
b101 B
b1 '
b1 .
b10 (
b10 -
b1 0
b1 /
#925
0!
0$
#930
1!
1$
b10000110000010000001111101001 J
b1010100 A
b110 B
b10000110000010000001111101001 +
#935
0!
0$
#940
1!
1$
b10 H
b1 I
b1010101 A
b1 4
b10010 :
b1 B
b10010 '
b10011 E
#945
0!
0$
#950
1!
1$
b100110110010000000000000001 J
b1010110 A
b10 B
b1 '
b100110110010000000000000001 +
#955
0!
0$
#960
1!
1$
b10000110000010000001111101001 J
b1010111 A
b100110110010000000000000001 ;
b11 B
b10000110000010000001111101001 +
#965
0!
0$
#970
1!
1$
b1011000 A
b10 3
b11 <
b11 =
b100 B
b10 ,
b100 0
b100 /
#975
0!
0$
#980
1!
1$
b11 G
b1010 F
b1 G
b1 F
b1011001 A
b1010 1
b101 B
b1010 (
b1010 -
b10100 0
b10100 /
#985
0!
0$
#990
1!
1$
b1011010 A
b10100 ?
b110 B
#995
0!
0$
#1000
1!
1$
b11 H
b10100 I
b1011011 A
b10100 5
b10011 :
b1 B
b10011 '
b10100 E
#1005
0!
0$
#1010
1!
1$
b100100000000000000000000001011 J
b1011100 A
b10 B
b1 '
b100100000000000000000000001011 +
#1015
0!
0$
#1020
1!
1$
b10000110000010000001111101001 J
b1011101 A
b100100000000000000000000001011 ;
b11 B
b10000110000010000001111101001 +
#1025
0!
0$
#1030
1!
1$
b1011110 A
b10010 3
b0 <
b0 =
b0 >
b1011 @
b100 B
b10010 ,
b0 0
b0 /
#1035
0!
0$
#1040
1!
1$
b0 G
b0 F
b1011111 A
b0 1
b0 2
b101 B
b0 '
b0 .
b0 (
b0 -
b1 0
b1 /
#1045
0!
0$
#1050
1!
1$
b10000100000010000001111101000 J
b1100000 A
b1 ?
b110 B
b10000100000010000001111101000 +
#1055
0!
0$
#1060
1!
1$
b111 H
b10011 I
b1100001 A
b10011 9
b1011 :
b1 B
b1011 '
b1100 E
#1065
0!
0$
#1070
1!
1$
b100100000101100000000000011010 J
b1100010 A
b10 B
b0 '
b100100000101100000000000011010 +
#1075
0!
0$
#1080
1!
1$
b10000100000010000001111101000 J
b1100011 A
b100100000101100000000000011010 ;
b11 B
b10000100000010000001111101000 +
#1085
0!
0$
#1090
1!
1$
b1100100 A
b10 =
b110 >
b11010 @
b100 B
#1095
0!
0$
#1100
1!
1$
b10 G
b1 F
b110 G
b1100101 A
b1 1
b1 2
b101 B
b1 '
b1 .
b1 (
b1 -
#1105
0!
0$
#1110
1!
1$
b10000110000010000001111101001 J
b1100110 A
b110 B
b10000110000010000001111101001 +
#1115
0!
0$
#1120
1!
1$
b1011 I
b1100111 A
b1011 9
b11010 :
b1 B
b11010 '
b11011 E
#1125
0!
0$
#1130
1!
1$
b100010000001010000000000011100 J
b1101000 A
b10 B
b1 '
b100010000001010000000000011100 +
#1135
0!
0$
#1140
1!
1$
b10000110000010000001111101001 J
b1101001 A
b100010000001010000000000011100 ;
b11 B
b10000110000010000001111101001 +
#1145
0!
0$
#1150
1!
1$
b1101010 A
b10001 3
b0 =
b101 >
b11100 @
b100 B
b10001 ,
#1155
0!
0$
#1160
1!
1$
b0 G
b0 F
b101 G
b11111111111111111111111111110100 F
b1101011 A
b0 1
b11111111111111111111111111110100 2
b101 B
b1111111111110100 '
b11111111111111111111111111110100 .
b0 (
b0 -
b0 0
b0 /
#1165
0!
0$
#1170
1!
1$
bx J
b1101100 A
b0 ?
b110 B
bx +
#1175
0!
0$
#1180
1!
1$
b1101101 A
b11011 :
b1 B
b11011 '
b11100 E
#1185
0!
0$
#1190
1!
1$
b10110000110000000000000000 J
b1101110 A
b10 B
b1111111111110100 '
b10110000110000000000000000 +
#1195
0!
0$
#1200
1!
1$
bx J
b1101111 A
b10110000110000000000000000 ;
b11 B
bx +
#1205
0!
0$
#1210
1!
1$
b1110000 A
b1 3
b11 <
b11 >
b0 @
b100 B
b1 ,
b1100 0
b1100 /
#1215
0!
0$
#1220
1!
1$
b0 G
b0 F
b11 G
b10100 F
b1110001 A
b10100 2
b101 B
b10100 '
b10100 .
b11111111111111111111111111101100 0
b11111111111111111111111111101100 /
#1225
0!
0$
#1230
1!
1$
b1000100000000000000000000 J
b1110010 A
b11111111111111111111111111101100 ?
b110 B
b1000100000000000000000000 +
#1235
0!
0$
#1240
1!
1$
b11 H
b11111111111111111111111111101100 I
b1110011 A
b11111111111111111111111111101100 5
b11100 :
b1 B
b11100 '
b11101 E
#1245
0!
0$
#1250
1!
1$
b10010000110010000001111101010 J
b1110100 A
b10 B
b10100 '
b10010000110010000001111101010 +
#1255
0!
0$
#1260
1!
1$
b1000100000000000000000000 J
b1110101 A
b10010000110010000001111101010 ;
b11 B
b1000100000000000000000000 +
#1265
0!
0$
#1270
1!
1$
b1110110 A
b1001 3
b0 <
b11 =
b1 >
b1111101010 @
b100 B
b1001 ,
#1275
0!
0$
#1280
1!
1$
b11111111111111111111111111101100 F
b1 G
b1111101010 F
b1110111 A
b11111111111111111111111111101100 1
b1111101010 2
b101 B
b1111101010 '
b1111101010 .
b11111111111111111111111111101100 (
b11111111111111111111111111101100 -
#1285
0!
0$
#1290
1!
1$
b0 J
b1111000 A
b110 B
1*
b0 +
#1295
0!
0$
#1300
1!
1$
b1111001 A
b11101 :
b1 B
0*
b11101 '
b11110 E
#1305
0!
0$
#1310
1!
1$
b110000000000000000000000000000 J
b1111010 A
b10 B
b1111101010 '
b110000000000000000000000000000 +
#1315
0!
0$
#1320
1!
1$
b11111111111111111111111111101100 J
b1111011 A
b110000000000000000000000000000 ;
b11 B
b11111111111111111111111111101100 +
#1325
0!
0$
#1330
1!
1$
b1111100 A
b11000 3
b0 =
b0 >
b0 @
b100 B
b11000 ,
#1335
0!
0$
#1340
1!
1$
b0 G
b0 F
b1111101 A
b0 1
b0 2
b101 B
b0 '
b0 .
b0 (
b0 -
#1345
0!
0$
#1350
1!
1$
b10000100000010000001111101000 J
b1111110 A
b110 B
b10000100000010000001111101000 +
